orodha_user_client/__init__.py
orodha_user_client/client.py
orodha_user_client/exceptions.py
orodha_user_client-1.0.dist-info/METADATA
orodha_user_client-1.0.dist-info/WHEEL
orodha_user_client-1.0.dist-info/licenses/LICENSE
orodha_user_client-1.0.dist-info/RECORD
