Metadata-Version: 2.1
Name: orodha-user-client
Version: 1.0
Summary: A software development kit used by Orodha services to interface with the Orodha user service.
Author-email: Edison Stuart <edisonstaurt@gmail.com>
License-File: LICENSE
Classifier: License :: OSI Approved :: MIT License
Classifier: Programming Language :: Python :: 3
Requires-Python: >=3.7
Requires-Dist: orodha-keycloak>=1.2.0
Requires-Dist: requests>=2.31.0
